tunica/fields.py
tunica-0.0.1.dist-info/LICENSE
tunica-0.0.1.dist-info/WHEEL
tunica-0.0.1.dist-info/METADATA
tunica-0.0.1.dist-info/RECORD
