Metadata-Version: 2.1
Name: tunica
Version: 0.0.1
Summary: Light-weight Python ORM
License: MIT
Author: Vladimir Minev
Author-email: minev.dev@gmail.com
Requires-Python: >=3.11,<4.0
Classifier: License :: OSI Approved :: MIT License
Classifier: Programming Language :: Python :: 3
Classifier: Programming Language :: Python :: 3.11
Requires-Dist: isort (>=5.12.0,<6.0.0)
Requires-Dist: pre-commit (>=3.2.2,<4.0.0)
Requires-Dist: pydantic (>=1.10.7,<2.0.0)
Requires-Dist: pytest (>=7.2.2,<8.0.0)
